[
 {
   "id": "pink1",
   "name": "pink1",
   "file": "chibi-parts/gacha/eyes/pink1.png",
   "category": "eyes",
   "cost": 1000,
   "stars": 4,
   "z_index": 10,
   "transform": { "x": 0, "y": 10, "scale": 28 }
 },
 {
   "id": "猫の目",
   "name": "猫の目",
   "file": "chibi-parts/gacha/eyes/猫の目.png",
   "category": "eyes",
   "cost": 1000,
   "stars": 4,
   "z_index": 10,
   "transform": { "x": -0.5, "y": 9, "scale": 37 }
 },
 {
   "id": "猫耳の瞳 (1)",
   "name": "猫耳の瞳 (1)",
   "file": "chibi-parts/gacha/eyes/猫耳の瞳 (1).png",
   "category": "eyes",
   "cost": 1000,
   "stars": 4,
   "z_index": 10,
   "transform": { "x": -0.5, "y": 10.5, "scale": 29 }
 },
 {
   "id": "エクステピンクツインテール",
   "name": "エクステピンクツインテール",
   "file": "chibi-parts/gacha/accessories/エクステピンクツインテール.png",
   "category": "accessories",
   "cost": 1000,
   "stars": 4,
   "z_index": 10,
   "transform": { "x": -0.5, "y": -6.5, "scale": 89 }
 },
 {
   "id": "パジャマグレー",
   "name": "パジャマグレー",
   "file": "chibi-parts/gacha/tops/パジャマグレー.png",
   "category": "tops",
   "cost": 1000,
   "stars": 4,
   "z_index": 10,
   "transform": { "x": 0, "y": 27.5, "scale": 39 }
 },
 {
   "id": "ぱじゃま黄色",
   "name": "ぱじゃま黄色",
   "file": "chibi-parts/gacha/tops/ぱじゃま黄色.png",
   "category": "tops",
   "cost": 1000,
   "stars": 4,
   "z_index": 10,
   "transform": { "x": -2, "y": 29, "scale": 43 }
 },
 {
   "id": "パジャマ黒",
   "name": "パジャマ黒",
   "file": "chibi-parts/gacha/tops/パジャマ黒.png",
   "category": "tops",
   "cost": 1000,
   "stars": 4,
   "z_index": 10,
   "transform": { "x": 0.5, "y": 28.5, "scale": 45 }
 },
 {
   "id": "ぱじゃま紫",
   "name": "ぱじゃま紫",
   "file": "chibi-parts/gacha/tops/ぱじゃま紫.png",
   "category": "tops",
   "cost": 1000,
   "stars": 4,
   "z_index": 10,
   "transform": { "x": 0.5, "y": 28.5, "scale": 41.5 }
 },
 {
   "id": "パジャマ水色",
   "name": "パジャマ水色",
   "file": "chibi-parts/gacha/tops/パジャマ水色.png",
   "category": "tops",
   "cost": 1000,
   "stars": 4,
   "z_index": 10,
   "transform": { "x": 0.5, "y": 28.5, "scale": 41.5 }
 },
 {
   "id": "パジャマ白",
   "name": "パジャマ白",
   "file": "chibi-parts/gacha/tops/パジャマ白.png",
   "category": "tops",
   "cost": 1000,
   "stars": 4,
   "z_index": 10,
   "transform": { "x": 0.5, "y": 27, "scale": 41.5 }
 },
 {
   "id": "ピンクジャージ",
   "name": "ピンクジャージ",
   "file": "chibi-parts/gacha/tops/ピンクジャージ.png",
   "category": "tops",
   "cost": 1000,
   "stars": 4,
   "z_index": 10,
   "transform": { "x": 0.5, "y": 35.5, "scale": 55.5 }
 },
 {
   "id": "ピンクのスウェット",
   "name": "ピンクのスウェット",
   "file": "chibi-parts/gacha/tops/ピンクのスウェット.png",
   "category": "tops",
   "cost": 1000,
   "stars": 4,
   "z_index": 10,
   "transform": { "x": -1, "y": 7.5, "scale": 78 }
 },
 {
   "id": "黒ジャージ",
   "name": "黒ジャージ",
   "file": "chibi-parts/gacha/tops/黒ジャージ.png",
   "category": "tops",
   "cost": 1000,
   "stars": 4,
   "z_index": 10,
   "transform": { "x": 2, "y": 35.5, "scale": 55 }
 },
 {
   "id": "青ジャージ",
   "name": "青ジャージ",
   "file": "chibi-parts/gacha/tops/青ジャージ.png",
   "category": "tops",
   "cost": 1000,
   "stars": 4,
   "z_index": 10,
   "transform": { "x": 2, "y": 35.5, "scale": 55 }
 },
 {
   "id": "白ジャージ",
   "name": "白ジャージ",
   "file": "chibi-parts/gacha/tops/白ジャージ.png",
   "category": "tops",
   "cost": 1000,
   "stars": 4,
   "z_index": 10,
   "transform": { "x": 2, "y": 35.5, "scale": 55 }
 },
 {
   "id": "猫口1",
   "name": "猫口1",
   "file": "chibi-parts/gacha/mouth/猫口1.png",
   "category": "mouth",
   "cost": 1000,
   "stars": 4,
   "z_index": 10,
   "transform": { "x": -1, "y": 8.5, "scale": 11 }
 },
 {
   "id": "猫口2",
   "name": "猫口2",
   "file": "chibi-parts/gacha/mouth/猫口2.png",
   "category": "mouth",
   "cost": 1000,
   "stars": 4,
   "z_index": 10,
   "transform": { "x": -1, "y": 8.5, "scale": 11 }
 },
 {
   "id": "ウサ耳と魔女帽",
   "name": "ウサ耳と魔女帽",
   "file": "chibi-parts/gacha/hair/ウサ耳と魔女帽.png",
   "category": "hair",
   "cost": 1000,
   "stars": 4,
   "z_index": 10,
   "transform": { "x": 1.5, "y": 22.5, "scale": 160 }
 },
 {
   "id": "セーラー服帽子",
   "name": "セーラー服帽子",
   "file": "chibi-parts/gacha/hair/セーラー服帽子.png",
   "category": "hair",
   "cost": 1000,
   "stars": 4,
   "z_index": 10,
   "transform": { "x": 1, "y": -5, "scale": 61 }
 },
 {
   "id": "セーラー服",
   "name": "セーラー服",
   "file": "chibi-parts/gacha/tops/セーラー服.png",
   "category": "tops",
   "cost": 1000,
   "stars": 4,
   "z_index": 10,
   "transform": { "x": 0.5, "y": 19.5, "scale": 37.5 }
 }
]
